LICENSE
MANIFEST.in
README.md
pyproject.toml
setup.py
django_static_mathjax.egg-info/PKG-INFO
django_static_mathjax.egg-info/SOURCES.txt
django_static_mathjax.egg-info/dependency_links.txt
django_static_mathjax.egg-info/top_level.txt
mathjax/__init__.py
mathjax/static/mathjax/.git
mathjax/static/mathjax/.gitignore
mathjax/static/mathjax/.travis.yml
mathjax/static/mathjax/CONTRIBUTING.md
mathjax/static/mathjax/LICENSE
mathjax/static/mathjax/README.md
mathjax/static/mathjax/package-lock.json
mathjax/static/mathjax/package.json
mathjax/static/mathjax/tsconfig.json
mathjax/static/mathjax/tslint.json
mathjax/static/mathjax/.github/ISSUE_TEMPLATE/bug_report.md
mathjax/static/mathjax/.github/ISSUE_TEMPLATE/feature_request.md
mathjax/static/mathjax/.github/ISSUE_TEMPLATE/mathjax-source-problem.md
mathjax/static/mathjax/components/webpack.common.js
mathjax/static/mathjax/components/bin/build
mathjax/static/mathjax/components/bin/copy
mathjax/static/mathjax/components/bin/makeAll
mathjax/static/mathjax/components/bin/pack
mathjax/static/mathjax/components/bin/version
mathjax/static/mathjax/components/src/dependencies.js
mathjax/static/mathjax/components/src/source.js
mathjax/static/mathjax/components/src/a11y/assistive-mml/assistive-mml.js
mathjax/static/mathjax/components/src/a11y/assistive-mml/build.json
mathjax/static/mathjax/components/src/a11y/assistive-mml/webpack.config.js
mathjax/static/mathjax/components/src/a11y/complexity/build.json
mathjax/static/mathjax/components/src/a11y/complexity/complexity.js
mathjax/static/mathjax/components/src/a11y/complexity/webpack.config.js
mathjax/static/mathjax/components/src/a11y/explorer/build.json
mathjax/static/mathjax/components/src/a11y/explorer/explorer.js
mathjax/static/mathjax/components/src/a11y/explorer/webpack.config.js
mathjax/static/mathjax/components/src/a11y/semantic-enrich/build.json
mathjax/static/mathjax/components/src/a11y/semantic-enrich/semantic-enrich.js
mathjax/static/mathjax/components/src/a11y/semantic-enrich/webpack.config.js
mathjax/static/mathjax/components/src/a11y/sre/build.json
mathjax/static/mathjax/components/src/a11y/sre/sre.js
