Metadata-Version: 2.1
Name: django-static-mathjax
Version: 3.2.2.1
Summary: JavaScript library for displaying mathematics on the Web
Maintainer-email: Benjamin Moody <bmoody@mit.edu>
Classifier: Development Status :: 5 - Production/Stable
Classifier: Environment :: Web Environment
Classifier: Framework :: Django
Classifier: License :: OSI Approved :: Apache Software License
Classifier: Programming Language :: JavaScript
Classifier: Topic :: Text Processing :: Markup :: LaTeX
License-File: LICENSE
